tapi_yandex_metrika/__init__.py
tapi_yandex_metrika/exceptions.py
tapi_yandex_metrika/resource_mapping.py
tapi_yandex_metrika/tapi_yandex_metrika.py
tapi_yandex_metrika-2019.9.29.dist-info/LICENSE
tapi_yandex_metrika-2019.9.29.dist-info/METADATA
tapi_yandex_metrika-2019.9.29.dist-info/WHEEL
tapi_yandex_metrika-2019.9.29.dist-info/top_level.txt
tapi_yandex_metrika-2019.9.29.dist-info/RECORD
